factool/__init__.py
factool/env_config.py
factool/factool.py
factool/tasks.py
factool/code/__init__.py
factool/code/pipeline.py
factool/code/tool.py
factool/code/helper/__init__.py
factool/code/helper/_execution.py
factool/code/helper/execution.py
factool/code/helper/io_utils.py
factool/code/helper/postprocess.py
factool/knowledge_qa/__init__.py
factool/knowledge_qa/google_serper.py
factool/knowledge_qa/pipeline.py
factool/knowledge_qa/tool.py
factool/math/__init__.py
factool/math/pipeline.py
factool/math/tool.py
factool/med_doc_qa/__init__.py
factool/med_doc_qa/pipeline.py
factool/scientific/__init__.py
factool/scientific/pipeline.py
factool/scientific/tool.py
factool/utils/__init_.py
factool/utils/claim_extractor.py
factool/utils/openai_wrapper.py
factool/utils/utils_json.py
factool/utils/base/__init__.py
factool/utils/base/pipeline.py
factool/utils/prompts/agreement_verification.yaml
factool/utils/prompts/claim_extraction.yaml
factool/utils/prompts/query_generation.yaml
factool/utils/prompts/self_check.yaml
factool-0.1.3.dist-info/METADATA
factool-0.1.3.dist-info/WHEEL
factool-0.1.3.dist-info/top_level.txt
factool-0.1.3.dist-info/RECORD
