Metadata-Version: 2.1
Name: factool
Version: 0.1.3
Summary: Factuality Detection for Generative AI
Home-page: https://github.com/GAIR-NLP/factool
Author: GAIR Research Group
License: Apache License
Platform: UNKNOWN
Classifier: Intended Audience :: Developers
Classifier: Topic :: Text Processing
Classifier: Topic :: Scientific/Engineering :: Artificial Intelligence
Classifier: License :: OSI Approved :: Apache Software License
Classifier: Programming Language :: Python :: 3.9
Classifier: Programming Language :: Python :: 3.10
Classifier: Programming Language :: Python :: 3 :: Only
Requires-Dist: openai ==0.27.8
Requires-Dist: PyYAML ==6.0
Requires-Dist: asyncio ==3.4.3
Requires-Dist: numpy
Requires-Dist: pydantic ==1.10.9
Requires-Dist: scholarly ==1.7.11
Requires-Dist: scikit-learn
Requires-Dist: aiohttp ==3.8.4
Requires-Dist: fastapi ==0.96.0
Requires-Dist: uvicorn ==0.22.0
Requires-Dist: jsonlines
